<?xml version="1.0" encoding="utf-8"?>
<!DOCTYPE hibernate-mapping PUBLIC "-//Hibernate/Hibernate Mapping DTD 3.0//EN"
"http://hibernate.sourceforge.net/hibernate-mapping-3.0.dtd">
<!-- 
    Mapping file autogenerated by MyEclipse Persistence Tools
-->
<hibernate-mapping>
    <class name="com.management.entity.SA09" table="SA09">
        <id name="SAE001">
        	<generator class="assigned" />
        </id>
        <property name="SAE002"></property>
        <property name="SAE003"></property>
        <property name="SAE004"></property>
        <property name="SAE005"></property>
        <property name="SAE006"></property>
        <property name="SAE007"></property>
        <property name="SAE008"></property>
        <property name="SAE009"></property>
        <property name="ZZB001"></property>
        <property name="ZZB002"></property>
        <property name="ZZD001"></property>
        <property name="ZZD002"></property>
        <property name="ZZE001"></property>
        <property name="ZZE002"></property>
    </class>
</hibernate-mapping>
